aiii_Javharbek/__init__.py
aiii_Javharbek/my_module.py
aiii_Javharbek-0.54.dist-info/METADATA
aiii_Javharbek-0.54.dist-info/WHEEL
aiii_Javharbek-0.54.dist-info/top_level.txt
aiii_Javharbek-0.54.dist-info/RECORD
