Metadata-Version: 2.1
Name: aiii_Javharbek
Version: 0.54
Summary: AIII
Author: Javharbek
Author-email: jakharbek@gmail.com
Classifier: Programming Language :: Python :: 3
Classifier: License :: OSI Approved :: MIT License
Classifier: Operating System :: OS Independent
Requires-Python: >=3.6
Requires-Dist: opencv-python==4.8.0.76
Requires-Dist: numpy==1.25.2
Requires-Dist: scipy==1.11.4
Requires-Dist: matplotlib==3.7.1
Requires-Dist: tensorflow==2.17.0
Requires-Dist: keras==3.5.0
Requires-Dist: imgaug==0.4.0
Requires-Dist: scikit-learn==1.2.2
Requires-Dist: shapely==2.0.5
Requires-Dist: deskew==1.5.1
